<?xml version="1.0" encoding="utf-8" ?>
<Defs>
  <MemeGroupDef>
    <defName>SexualDissolutely</defName>
    <drawOffset>(0.65, 0.23)</drawOffset>
    <maxRows>1</maxRows>
    <renderOrder>3000</renderOrder>
  </MemeGroupDef>

  <MemeDef Name="SexualDissoulutelyBase" Abstract="True">
    <groupDef>SexualDissolutely</groupDef>
    <selectOneOrNone>
      <noneChance>1.0</noneChance>
      <preceptThingPairs>
      </preceptThingPairs>
    </selectOneOrNone>
  </MemeDef>

  <MemeDef ParentName="SexualDissoulutelyBase">
    <defName>Zoophile</defName>
    <label>zoophile</label>
    <description>Animal fuckers.</description>
    <iconPath>UI/Commands/Breeding_Pawn_off</iconPath>
    <impact>3</impact>
    <requireOne>
      <li>
        <li>Bestiality_Acceptable</li>
        <li>Bestiality_OnlyVenerated</li>
        <li>Bestiality_Honorable</li>
      </li>
    </requireOne>
    <generalRules>
      <rulesStrings>
        <li>memeAdjective->bestial</li>
        <li>memeAdjective->zoophile</li>
        <li>memeHyphenPrefix->bestial</li>
        <li>memeConcept->breeding</li>
        <li>memeConcept->bestiality</li>
        <li>memeConcept->zoophile</li>
        <li>memeLeaderNoun->livestock</li>
      </rulesStrings>
    </generalRules>
    <descriptionMaker>
      <rules>
        <rulesStrings>
          <!-- theist myth -->
          <li>creation(tag=meme_Zoophile)        ->[deity0_name] loves breeding with beasts.</li>
          <li>episode(uses=1,tag=meme_Zoophile)  ->[deity0_name] said to all, "Sigmar forbids this!"</li>
          <!-- ideological founder -->
          <li>setup(tag=meme_Zoophile)           ->Someday, [founderName] was so horny that accidentally fucked with an animal and loved it. </li>
          <li>story(uses=1,tag=meme_Zoophile)    ->For spreading animals, [founderName] started to breed with animals.</li>
          <!-- ideological lesson -->
          <li>lessonIntro(tag=meme_Zoophile)         ->Someday, i had sex with animal. It was much better than humans!</li>
          <li>lesson(tag=meme_Zoophile)              ->Only the animals can satisfy me.</li>
          <li>lessonReinforcement(tag=meme_Zoophile) ->Breed with animals. It is the eternal hapiness.</li>
          <!-- archist -->
          <li>archistBasis(tag=meme_Zoophile)    ->Archists are always seeking ultimate pleasure.</li>
          <li>archistFact(tag=meme_Zoophile)     ->That was breeding with animals.</li>
          <li>archistProphecy(tag=meme_Zoophile) ->[inTheEnd], the archotechs will finally unlock the interspecies breeding, so that they may lead ultimate pleasure.</li>
          <!-- animist -->
          <li>animistFact(tag=meme_Zoophile)     ->The most powerful spirits are those of beasts, and spirits of beasts will be restless unless beasts rule.</li>
          <li>animistProphecy(tag=meme_Zoophile) ->[itIsSaid] that a powerful spirit of destruction will seek to end the universe, but that a human-born beast will wield the spirit of the [relic0_name] and destroy the destroyer.</li>
        </rulesStrings>
      </rules>
    </descriptionMaker>
    <symbolPacks>
      <li>
        <ideoName>Breeders</ideoName>
        <theme>breed</theme>
        <adjective>bestiality</adjective>
        <member>breeder</member>
      </li>
      <li>
        <ideoName>Zoophilia</ideoName>
        <theme>zoophile</theme>
        <adjective>zoophile</adjective>
        <member>zoophiliac</member>
      </li>
    </symbolPacks>
    <agreeableTraits>
      <li>Zoophile</li>
    </agreeableTraits>
  </MemeDef>


  <MemeDef ParentName="SexualDissoulutelyBase">
    <defName>Rapist</defName>
    <label>rapist</label>
    <description>Rape is best.</description>
    <iconPath>UI/Memes/Rape</iconPath>
    <impact>2</impact>
    <requireOne>
      <li>
        <li>Rape_Honorable</li>
        <li>Rape_Acceptable</li>
      </li>
    </requireOne>
    <generalRules>
      <rulesStrings>
        <li>memeAdjective->violent</li>
        <li>memeAdjective->raping</li>
        <li>memeHyphenPrefix->rapist</li>
        <li>memeHyphenPrefix->molester</li>
        <li>memeHyphenPrefix->pervert</li>
        <li>memeConcept->rapist</li>
        <li>memeConcept->pervert</li>
        <li>memeGod->slaanesh</li>
        <li>memeLeaderNoun->stallion</li>
        <li>memeLeaderNoun->grand rapist</li>
      </rulesStrings>
    </generalRules>
    <descriptionMaker>
      <rules>
        <rulesStrings>
          <!-- theist myth -->
          <li>creation(tag=meme_Rapist)        ->[deity0_name] loves rape.</li>
          <li>episode(uses=1,tag=meme_Rapist)  ->[deity0_name] raped everyone until death during rape.</li>
          <!-- ideological founder -->
          <li>setup(tag=meme_Rapist)           ->[founderName] is always horny. </li>
          <li>story(uses=1,tag=meme_Rapist)    ->[founderName] raped everyone. No one can stop [founderName]. [founderName] died trying to rape planet.</li>
          <!-- ideological lesson -->
          <li>lessonIntro(tag=meme_Rapist)         ->Rape is best! Rape is best! Rape is best!</li>
          <li>lesson(tag=meme_Rapist)              ->Rape is best! Rape is best! Rape is best! Rape is best!</li>
          <li>lessonReinforcement(tag=meme_Rapist) ->Rape is best! Rape is best! Rape is best! Rape is best! Rape is best!</li>
          <!-- archist -->
          <li>archistBasis(tag=meme_Rapist)    ->Human history is history of rape.</li>
          <li>archistFact(tag=meme_Rapist)     ->Even archotechs cannot stop rapists.</li>
          <li>archistProphecy(tag=meme_Rapist) ->[inTheEnd], the rapists never stop raping.</li>
          <!-- animist -->
          <li>animistFact(tag=meme_Rapist)     ->The most powerful spirits are those of rapists, and spirits of rapists will rape all.</li>
          <li>animistProphecy(tag=meme_Rapist) ->[itIsSaid] that a powerful spirit of destruction will seek to end the universe, but that a million-raped rapist will wield the spirit of the [relic0_name] and rape the destroyer.</li>
        </rulesStrings>
      </rules>
    </descriptionMaker>
    <symbolPacks>
      <li>
        <ideoName>Rapists</ideoName>
        <theme>rapist</theme>
        <adjective>raping</adjective>
        <member>rapist</member>
      </li>
      <li>
        <ideoName>Cult of Slaanesh</ideoName>
        <theme>pleasure</theme>
        <adjective>decadent</adjective>
        <member>heretic</member>
      </li>
    </symbolPacks>
    <agreeableTraits>
      <li>Rapist</li>
    </agreeableTraits>
  </MemeDef>

  <MemeDef ParentName="SexualDissoulutelyBase">
    <defName>Lewd</defName>
    <label>lewd</label>
    <description>Perverts.</description>
    <iconPath>UI/Memes/SexualDissolutely</iconPath>
    <impact>3</impact>
    <consumableBuildings>
      <li>Burnbong_Aphrodisiac</li>
    </consumableBuildings>
    <requireOne>
      <li>
        <li>Lovin_FreeApproved</li>
      </li>
      <li>
        <li>Incestuos_Free</li>
      </li>
      <li>
        <li>Sex_Free</li>
        <li>Sex_Promiscuous</li>
      </li>
    </requireOne>
    <requiredRituals>
      <li>
        <precept>DateRitualConsumable</precept>
        <pattern>DrugOrgy</pattern>
        <building>Burnbong_Aphrodisiac</building>
      </li>
    </requiredRituals>
    <generalRules>
      <rulesStrings>
        <li>memeAdjective->horny</li>
        <li>memeAdjective->lewd</li>
        <li>memeAdjective->arousing</li>
        <li>memeAdjective->sexy</li>
        <li>memeAdjective->estrous</li>
        <li>memeAdjective->decadent</li>
        <li>memeHyphenPrefix->estro</li>
        <li>memeHyphenPrefix->lust</li>
        <li>memeConcept->lust</li>
        <li>memeConcept->libido</li>
        <li>memeConcept->estrus</li>
        <li>memeConcept->arousal</li>
        <li>memeConcept->desire</li>
        <li>memeConcept->sex</li>
        <li>memeConcept->perversion</li>
        <li>memeGod->slaanesh</li>
      </rulesStrings>
    </generalRules>
    <symbolPacks>
      <li>
        <ideoName>Cult of Slaanesh</ideoName>
        <theme>pleasure</theme>
        <adjective>decadent</adjective>
        <member>heretic</member>
      </li>
    </symbolPacks>
    <addDesignators>
      <li>Autobong_Aphrodisiac</li>
    </addDesignators>
    <agreeableTraits>
      <li>Nymphomaniac</li>
    </agreeableTraits>
  </MemeDef>

  <MemeDef ParentName="SexualDissoulutelyBase">
    <defName>Necrophile</defName>
    <label>necrophile</label>
    <description>Corpse fuckers.</description>
    <iconPath>UI/Memes/Necrophile</iconPath>
    <impact>2</impact>
    <requireOne>
      <li>
        <li>Necrophilia_Acceptable</li>
        <li>Necrophilia_Approved</li>
      </li>
      <li>
        <li>Corpses_DontCare</li>
      </li>
    </requireOne>
    <generalRules>
      <rulesStrings>
        <li>memeGod->sonic</li>
        <li>memeGod->mega man</li>
      </rulesStrings>
    </generalRules>
    <agreeableTraits>
      <li>Necrophiliac</li>
    </agreeableTraits>
  </MemeDef>
</Defs>